l0n0l2fa/__init__.py
l0n0l2fa/main.py
l0n0l2fa/migrate_tokens.py
l0n0l2fa/加解密.py
l0n0l2fa-2.0.2.dist-info/METADATA
l0n0l2fa-2.0.2.dist-info/WHEEL
l0n0l2fa-2.0.2.dist-info/entry_points.txt
l0n0l2fa-2.0.2.dist-info/top_level.txt
l0n0l2fa-2.0.2.dist-info/RECORD
