Metadata-Version: 2.1
Name: l0n0l2fa
Version: 2.0.2
Summary: TOTP 2FA
Project-URL: Homepage, https://gitee.com/l00n00l/l0n0l2fa
Requires-Python: >=3.8
Requires-Dist: aiohttp
Requires-Dist: pyotp
Requires-Dist: qrcode
Requires-Dist: cryptography
